FPU.sv
module FPMU#(
    parameter SIGN = 1,
    parameter WIDTH = 8, // Width of the input data
    parameter FP_POSITIONS = 4 // Number of positions for the fixed point representation
)(
    input logic [WIDTH-1:0] a, // Input A
    input logic [WIDTH-1:0] b, // Input B
    output logic [WIDTH-1:0] result // Result of the multiplication
);
    logic [2*WIDTH-1:0] product;
    assign product = SIGN ? $signed(a) * $signed(b) : a * b ; // Perform multiplication based on SIGN
            // Perform the multiplication and shift the result to the right by FP_POSITIONS
    assign result = product[WIDTH + FP_POSITIONS - 1:FP_POSITIONS];

endmodule

MU.sv
module MU#(
    parameter WIDTH = 8,
    parameter kernel_size = 5,
    parameter SIGN = 1, // 1 for signed, 0 for unsigned
    parameter FP_POSITIONS = 4 
)(
    input logic clk,
    input logic rst_n, // Active low reset
    input logic weight_valid,
    input logic data_valid,
    input logic [WIDTH - 1:0] weight,
    input logic [WIDTH - 1:0] data, // Input data
    input logic [WIDTH - 1:0] bias, // Bias for the multiplication
    output logic [WIDTH - 1:0] conv_result, // Result of the multiplication
    output logic conv_result_valid // Output valid signal
);

    logic [$clog2(kernel_size*kernel_size)-1:0] counter, counter_next; // Counter for kernel size
    logic [WIDTH - 1:0] A,B,A_mult_B;
    logic [WIDTH - 1:0] conv_result_next;
    logic conv_result_valid_next;

    FPMU #(
        .SIGN(SIGN),
        .WIDTH(WIDTH),
        .FP_POSITIONS(FP_POSITIONS)
    ) fpmu (
        .a(A),
        .b(B),
        .result(A_mult_B)
    );

    always_ff @(posedge clk or negedge rst_n) begin
        if (!rst_n) begin
            counter <= 0; // Reset the counter to zero
            conv_result <= 0; // Reset the result to zero
            conv_result_valid <= 0; // Reset the valid signal
        end else begin
            // conv_result <= (counter == 0) ? A_mult_B + bias: A_mult_B + conv_result; // Add bias to the result
            // conv_result_valid <= (&counter); // Set the valid signal high
            // counter <= counter + 1; // Increment the counter
            conv_result <= conv_result_next; // Add bias to the result
            conv_result_valid <= conv_result_valid_next; // Set the valid signal high
            counter <= counter_next; // Increment the counter
        end
    end

    always_comb begin : comb_logic
        counter_next = counter; // Default to current counter value
        conv_result_next = conv_result; // Default to current result
        conv_result_valid_next = 0; // Default to current valid signal
        A = 0; // Reset A to zero
        B = 0; // Reset B to zero
        if (weight_valid && data_valid) begin
            A = weight; // Assign weight to A
            B = data; // Assign data to B
            conv_result_next = (counter == 0) ? A_mult_B + bias: A_mult_B + conv_result; // Add bias to the result
            conv_result_valid_next = (counter == kernel_size * kernel_size - 1); // Set the valid signal high
            counter_next = (counter ==kernel_size* kernel_size - 1) ? 0 : counter + 1; // Increment the counter
        end 
    end
endmodule

MU_tb.sv
`timescale 1ns/1ps

module MU_tb;
    // Parameters
    localparam WIDTH = 8;
    localparam kernel_size = 3;
    localparam SIGN = 1;
    localparam FP_POSITIONS = 4;
    localparam CLK_PERIOD = 10; // Clock period in ns

    // Testbench signals
    logic clk;
    logic rst_n;
    logic weight_valid;
    logic data_valid;
    logic [WIDTH-1:0] weight;
    logic [WIDTH-1:0] data;
    logic [WIDTH-1:0] bias;
    logic [WIDTH-1:0] conv_result;
    logic conv_result_valid;

    // Instantiate the DUT (Device Under Test)
    MU #(
        .WIDTH(WIDTH),
        .kernel_size(kernel_size),
        .SIGN(SIGN),
        .FP_POSITIONS(FP_POSITIONS)
    ) dut (
        .clk(clk),
        .rst_n(rst_n),
        .weight_valid(weight_valid),
        .data_valid(data_valid),
        .weight(weight),
        .data(data),
        .bias(bias),
        .conv_result(conv_result),
        .conv_result_valid(conv_result_valid)
    );

    // Clock generation
    initial begin
        clk = 0;
        forever #(CLK_PERIOD/2) clk = ~clk;
    end

    // Test stimulus
    initial begin
        // Initialize signals
        rst_n = 0;
        weight_valid = 0;
        data_valid = 0;
        weight = 0;
        data = 0;
        bias = 8'h10; // Example bias value (16 in decimal)

        // Reset sequence
        #20;
        rst_n = 1;
        #20;

        // Test case 1: Simple convolution
        // Send kernel_size*kernel_size (9) pairs of weights and data
        for (int i = 0; i < kernel_size*kernel_size; i++) begin
            weight_valid = 1;
            data_valid = 1;
            weight = 8'h02; // Weight = 2
            data = 8'h03;   // Data = 3
            #10;
        end

        // Wait for result
        weight_valid = 0;
        data_valid = 0;

        // Wait for computation to complete
        #50;

        // Test case 2: Reset during operation
        weight_valid = 1;
        data_valid = 1;
        weight = 8'h04; // Weight = 4
        data = 8'h05;   // Data = 5
        
        #20;
        rst_n = 0; // Assert reset
        #20;
        rst_n = 1; // Release reset

        // Test case 3: Different values
        for (int i = 0; i < kernel_size*kernel_size; i++) begin

            weight_valid = 1;
            data_valid = 1;
            weight = i + 1; // Incremental weights
            data = i + 2;   // Incremental data
            #10;
        end

        // Finish simulation
        #100;
        $display("Simulation completed");
        $finish;
    end

    // Monitor
    initial begin
        $monitor("Time=%0t rst_n=%b weight_valid=%b data_valid=%b weight=%h data=%h bias=%h conv_result=%h conv_result_valid=%b",
                 $time, rst_n, weight_valid, data_valid, weight, data, bias, conv_result, conv_result_valid);
    end

    // Dump variables for waveform viewing
    initial begin
        $dumpfile("MU_tb.vcd");
        $dumpvars(0, MU_tb);
    end
endmodule

MU_tb.vcd
$date
	Tue Apr 01 11:09:05 2025
$end
$version
	ModelSim Version 10.4
$end
$timescale
	1ps
$end

$scope module MU_tb $end
$var parameter 32 ! WIDTH $end
$var parameter 32 " kernel_size $end
$var parameter 32 # SIGN $end
$var parameter 32 $ FP_POSITIONS $end
$var parameter 32 % CLK_PERIOD $end
$var reg 1 & clk $end
$var reg 1 ' rst_n $end
$var reg 1 ( weight_valid $end
$var reg 1 ) data_valid $end
$var reg 8 * weight [7:0] $end
$var reg 8 + data [7:0] $end
$var reg 8 , bias [7:0] $end
$var reg 8 - conv_result [7:0] $end
$var reg 1 . conv_result_valid $end

$scope module dut $end
$var parameter 32 / WIDTH $end
$var parameter 32 0 kernel_size $end
$var parameter 32 1 SIGN $end
$var parameter 32 2 FP_POSITIONS $end
$var wire 1 3 clk $end
$var wire 1 4 rst_n $end
$var wire 1 5 weight_valid $end
$var wire 1 6 data_valid $end
$var wire 1 7 weight [7] $end
$var wire 1 8 weight [6] $end
$var wire 1 9 weight [5] $end
$var wire 1 : weight [4] $end
$var wire 1 ; weight [3] $end
$var wire 1 < weight [2] $end
$var wire 1 = weight [1] $end
$var wire 1 > weight [0] $end
$var wire 1 ? data [7] $end
$var wire 1 @ data [6] $end
$var wire 1 A data [5] $end
$var wire 1 B data [4] $end
$var wire 1 C data [3] $end
$var wire 1 D data [2] $end
$var wire 1 E data [1] $end
$var wire 1 F data [0] $end
$var wire 1 G bias [7] $end
$var wire 1 H bias [6] $end
$var wire 1 I bias [5] $end
$var wire 1 J bias [4] $end
$var wire 1 K bias [3] $end
$var wire 1 L bias [2] $end
$var wire 1 M bias [1] $end
$var wire 1 N bias [0] $end
$var reg 8 O conv_result [7:0] $end
$var reg 1 P conv_result_valid $end
$var reg 4 Q counter [3:0] $end
$var reg 4 R counter_next [3:0] $end
$var reg 8 S A [7:0] $end
$var reg 8 T B [7:0] $end
$var reg 8 U A_mult_B [7:0] $end
$var reg 8 V conv_result_next [7:0] $end
$var reg 1 W conv_result_valid_next $end

$scope begin comb_logic $end
$upscope $end

$scope module fpmu $end
$var parameter 32 X SIGN $end
$var parameter 32 Y WIDTH $end
$var parameter 32 Z FP_POSITIONS $end
$var wire 1 [ a [7] $end
$var wire 1 \ a [6] $end
$var wire 1 ] a [5] $end
$var wire 1 ^ a [4] $end
$var wire 1 _ a [3] $end
$var wire 1 ` a [2] $end
$var wire 1 a a [1] $end
$var wire 1 b a [0] $end
$var wire 1 c b [7] $end
$var wire 1 d b [6] $end
$var wire 1 e b [5] $end
$var wire 1 f b [4] $end
$var wire 1 g b [3] $end
$var wire 1 h b [2] $end
$var wire 1 i b [1] $end
$var wire 1 j b [0] $end
$var reg 8 k result [7:0] $end
$var reg 16 l product [15:0] $end
$upscope $end
$upscope $end
$upscope $end
$enddefinitions $end
#0
$dumpvars
0&
0'
0(
0)
b0 *
b0 +
b10000 ,
b0 -
0.
b0 O
0P
b0 Q
b0 R
b0 S
b0 T
b0 U
b0 V
0W
b0 k
b0 l
b1000 !
b11 "
b1 #
b100 $
b1010 %
b1000 /
b11 0
b1 1
b100 2
b1 X
b1000 Y
b100 Z
03
04
05
06
0>
0=
0<
0;
0:
09
08
07
0F
0E
0D
0C
0B
0A
0@
0?
0N
0M
0L
0K
1J
0I
0H
0G
0b
0a
0`
0_
0^
0]
0\
0[
0j
0i
0h
0g
0f
0e
0d
0c
$end
#5000
1&
13
#10000
0&
03
#15000
1&
13
#20000
1'
0&
14
03
#25000
1&
13
#30000
0&
03
#35000
1&
13
#40000
1(
1)
b10 *
b11 +
0&
15
16
1F
1E
1=
03
b10 S
b11 T
b10000 V
b1 R
1j
1i
1a
b110 l
#45000
1&
13
b10000 O
b1 Q
b10000 -
b0 S
b0 T
b10 S
b11 T
b10 R
#50000
0&
03
#55000
1&
13
b10 Q
b0 S
b0 T
b10 S
b11 T
b11 R
#60000
0&
03
#65000
1&
13
b11 Q
b0 S
b0 T
b10 S
b11 T
b100 R
#70000
0&
03
#75000
1&
13
b100 Q
b0 S
b0 T
b10 S
b11 T
b101 R
#80000
0&
03
#85000
1&
13
b101 Q
b0 S
b0 T
b10 S
b11 T
b110 R
#90000
0&
03
#95000
1&
13
b110 Q
b0 S
b0 T
b10 S
b11 T
b111 R
#100000
0&
03
#105000
1&
13
b111 Q
b0 S
b0 T
b10 S
b11 T
b1000 R
#110000
0&
03
#115000
1&
13
b1000 Q
b0 S
b0 T
b10 S
b11 T
1W
b0 R
#120000
0&
03
#125000
1&
13
1P
b0 Q
1.
0W
b0 S
b0 T
b10 S
b11 T
b1 R
#130000
0(
0)
0&
05
06
03
b0 R
b0 S
b0 T
0j
0i
0a
b0 l
#135000
1&
13
0P
0.
#140000
0&
03
#145000
1&
13
#150000
0&
03
#155000
1&
13
#160000
0&
03
#165000
1&
13
#170000
0&
03
#175000
1&
13
#180000
1(
1)
b100 *
b101 +
0&
15
16
0E
1D
0=
1<
03
b100 S
b101 T
b1 R
1j
1h
1`
b10100 l
b1 k
b1 U
b0 R
b0 S
b0 T
b100 S
b101 T
b10001 V
b1 R
#185000
1&
13
b10001 O
b1 Q
b10001 -
b0 S
b0 T
b100 S
b101 T
b10010 V
b10 R
#190000
0&
03
#195000
1&
13
b10010 O
b10 Q
b10010 -
b0 S
b0 T
b100 S
b101 T
b10011 V
b11 R
#200000
0'
0&
04
03
b0 Q
b0 O
b0 -
b0 R
b0 V
b0 S
b0 T
b100 S
b101 T
b10001 V
b1 R
#205000
1&
13
#210000
0&
03
#215000
1&
13
#220000
1'
b1 *
b10 +
0&
14
0F
1E
0D
1>
0<
03
b0 R
b0 V
b0 S
b0 T
b1 S
b10 T
b10001 V
b1 R
0j
1i
0h
1b
0`
b10 l
b0 k
b0 U
b0 R
b0 V
b0 S
b0 T
b1 S
b10 T
b10000 V
b1 R
#225000
1&
13
b10000 O
b1 Q
b10000 -
b0 S
b0 T
b1 S
b10 T
b10 R
#230000
b10 *
b11 +
0&
1F
0>
1=
03
b1 R
b0 S
b0 T
b10 S
b11 T
b10 R
1j
0b
1a
b110 l
#235000
1&
13
b10 Q
b0 S
b0 T
b10 S
b11 T
b11 R
#240000
b11 *
b100 +
0&
0F
0E
1D
1>
03
b10 R
b0 S
b0 T
b11 S
b100 T
b11 R
0j
0i
1h
1b
b1100 l
#245000
1&
13
b11 Q
b0 S
b0 T
b11 S
b100 T
b100 R
#250000
b100 *
b101 +
0&
1F
0>
0=
1<
03
b11 R
b0 S
b0 T
b100 S
b101 T
b100 R
1j
0b
0a
1`
b10100 l
b1 k
b1 U
b11 R
b0 S
b0 T
b100 S
b101 T
b10001 V
b100 R
#255000
1&
13
b10001 O
b100 Q
b10001 -
b0 S
b0 T
b100 S
b101 T
b10010 V
b101 R
#260000
b101 *
b110 +
0&
0F
1E
1>
03
b100 R
b10001 V
b0 S
b0 T
b101 S
b110 T
b10010 V
b101 R
0j
1i
1b
b11110 l
#265000
1&
13
b10010 O
b101 Q
b10010 -
b0 S
b0 T
b101 S
b110 T
b10011 V
b110 R
#270000
b110 *
b111 +
0&
1F
0>
1=
03
b101 R
b10010 V
b0 S
b0 T
b110 S
b111 T
b10011 V
b110 R
1j
0b
1a
b101010 l
b10 k
b10 U
b101 R
b10010 V
b0 S
b0 T
b110 S
b111 T
b10100 V
b110 R
#275000
1&
13
b10100 O
b110 Q
b10100 -
b0 S
b0 T
b110 S
b111 T
b10110 V
b111 R
#280000
b111 *
b1000 +
0&
0F
0E
0D
1C
1>
03
b110 R
b10100 V
b0 S
b0 T
b111 S
b1000 T
b10110 V
b111 R
0j
0i
0h
1g
1b
b111000 l
b11 k
b11 U
b110 R
b10100 V
b0 S
b0 T
b111 S
b1000 T
b10111 V
b111 R
#285000
1&
13
b10111 O
b111 Q
b10111 -
b0 S
b0 T
b111 S
b1000 T
b11010 V
b1000 R
#290000
b1000 *
b1001 +
0&
1F
0>
0=
0<
1;
03
b111 R
b10111 V
b0 S
b0 T
b1000 S
b1001 T
b11010 V
b1000 R
1j
0b
0a
0`
1_
b1001000 l
b100 k
b100 U
b111 R
b10111 V
b0 S
b0 T
b1000 S
b1001 T
b11011 V
b1000 R
#295000
1&
13
b11011 O
b1000 Q
b11011 -
b0 S
b0 T
b1000 S
b1001 T
b11111 V
1W
b0 R
#300000
b1001 *
b1010 +
0&
0F
1E
1>
03
b1000 R
b11011 V
0W
b0 S
b0 T
b1001 S
b1010 T
b11111 V
1W
b0 R
0j
1i
1b
b1011010 l
b101 k
b101 U
b1000 R
b11011 V
0W
b0 S
b0 T
b1001 S
b1010 T
b100000 V
1W
b0 R
#305000
1&
13
b100000 O
1P
b0 Q
1.
b100000 -
0W
b0 S
b0 T
b1001 S
b1010 T
b10101 V
b1 R
#310000
0&
03
#315000
1&
13
b10101 O
0P
b1 Q
0.
b10101 -
b0 S
b0 T
b1001 S
b1010 T
b11010 V
b10 R
#320000
0&
03
#325000
1&
13
b11010 O
b10 Q
b11010 -
b0 S
b0 T
b1001 S
b1010 T
b11111 V
b11 R
#330000
0&
03
#335000
1&
13
b11111 O
b11 Q
b11111 -
b0 S
b0 T
b1001 S
b1010 T
b100100 V
b100 R
#340000
0&
03
#345000
1&
13
b100100 O
b100 Q
b100100 -
b0 S
b0 T
b1001 S
b1010 T
b101001 V
b101 R
#350000
0&
03
#355000
1&
13
b101001 O
b101 Q
b101001 -
b0 S
b0 T
b1001 S
b1010 T
b101110 V
b110 R
#360000
0&
03
#365000
1&
13
b101110 O
b110 Q
b101110 -
b0 S
b0 T
b1001 S
b1010 T
b110011 V
b111 R
#370000
0&
03
#375000
1&
13
b110011 O
b111 Q
b110011 -
b0 S
b0 T
b1001 S
b1010 T
b111000 V
b1000 R
#380000
0&
03
#385000
1&
13
b111000 O
b1000 Q
b111000 -
b0 S
b0 T
b1001 S
b1010 T
b111101 V
1W
b0 R
#390000
0&
03
#395000
1&
13
b111101 O
1P
b0 Q
1.
b111101 -
0W
b0 S
b0 T
b1001 S
b1010 T
b10101 V
b1 R
#400000
0&
03
#405000
1&
13
b10101 O
0P
b1 Q
0.
b10101 -
b0 S
b0 T
b1001 S
b1010 T
b11010 V
b10 R
